metamenus/BaseMenuEx.py
metamenus/Configuration.py
metamenus/Constants.py
metamenus/MenuBarEx.py
metamenus/MenuEx.py
metamenus/SItem.py
metamenus/Singleton.py
metamenus/__init__.py
metamenus/metamenus.py
metamenus/mmprep.py
metamenus/types.py
metamenus/internal/ITypes.py
metamenus/internal/__init__.py
metamenus-0.14.4.dist-info/LICENSE
metamenus-0.14.4.dist-info/METADATA
metamenus-0.14.4.dist-info/WHEEL
metamenus-0.14.4.dist-info/entry_points.txt
metamenus-0.14.4.dist-info/top_level.txt
metamenus-0.14.4.dist-info/RECORD
