Metadata-Version: 2.1
Name: metamenus
Version: 0.14.4
Summary: Declarative Menu Maker for wxPython
Home-page: https://github.com/hasii2011/metamenus
Author: E.A. Tacao
Author-email: mailto@tacao.com.br
Maintainer: Humberto Sanchez II
Maintainer-email: humberto.a.sanchez.ii@gmail.com
License: UNKNOWN
Platform: UNKNOWN
License-File: LICENSE
Requires-Dist: wxPython
Requires-Dist: click
